<?xml version="1.0" encoding="utf-8" ?>
<widget
    id="incentro.whitelabelhelper.WhitelabelHelper"
    pluginWidget="true"
    needsEntityContext="true"
    offlineCapable="true"
    supportedPlatform="Web"
    xmlns="http://www.mendix.com/widget/1.0/"
    xmlns:xsi="http://www.w3.org/2001/XMLSchema-instance"
    xsi:schemaLocation="http://www.mendix.com/widget/1.0/ ../node_modules/mendix/custom_widget.xsd"
>
    <name>Whitelabel Helper</name>
    <description>Set dynamic CSS variables for whitelabeling your application.</description>
    <studioProCategory>Display</studioProCategory>
    <studioCategory>Display</studioCategory>
    <properties>
        <propertyGroup caption="General">
            <property key="CSSVariables" type="object" isList="true">
                <caption>CSS variables</caption>
                <description />
                <properties>
                    <propertyGroup caption="Object list group">
                        <property key="Property" type="string">
                            <caption>Variable name</caption>
                            <description>name-without-spaces</description>
                        </property>
                        <property key="Value" type="expression" defaultValue="'#BADA55'">
                            <caption>Variable value</caption>
                            <description>The value of the CSS variable. For example a color.</description>
                            <returnType type="String" />
                        </property>
                    </propertyGroup>
                </properties>
            </property>
        </propertyGroup>
    </properties>
</widget>
